wagtailblock/__init__.py
wagtailblock/register.py
wagtailblock_register-1.7.dist-info/LICENSE
wagtailblock_register-1.7.dist-info/METADATA
wagtailblock_register-1.7.dist-info/WHEEL
wagtailblock_register-1.7.dist-info/top_level.txt
wagtailblock_register-1.7.dist-info/RECORD
