Metadata-Version: 2.1
Name: wagtailblock-register
Version: 1.7
Summary: Register wagtailblocks with a simple decorator
Home-page: https://github.com/thomasBisseling/wagtailblock-register
Author: Thomas Bisseling
Author-email: thomasbisselinghall@gmail.com
License: BSD
Platform: UNKNOWN
Classifier: Development Status :: 5 - Production/Stable
Classifier: Environment :: Web Environment
Classifier: Intended Audience :: Developers
Classifier: License :: OSI Approved :: BSD License
Classifier: Operating System :: OS Independent
Classifier: Programming Language :: Python
Classifier: Programming Language :: Python :: 3
Classifier: Programming Language :: Python :: 3.5
Classifier: Programming Language :: Python :: 3.6
Classifier: Programming Language :: Python :: 3.7
Classifier: Programming Language :: Python :: 3.8
Classifier: Framework :: Django
Classifier: Framework :: Django :: 2.2
Classifier: Framework :: Django :: 3.0
Classifier: Framework :: Wagtail
Classifier: Topic :: Internet :: WWW/HTTP :: Site Management
Requires-Dist: wagtail
